{
  "$schema": "https://schemas.wp.org/trunk/block.json",
  "apiVersion": 3,
  "name": "easy-smart-login/login-form",
  "version": "0.1.0",
  "title": "Login Form",
  "category": "widgets",
  "icon": "lock",
  "description": "Example block scaffolded with Create Block tool.",
  "example": {},
  "supports": {
    "html": false
  },
  "textdomain": "easy-smart-login",
  "editorScript": "file:./index.js",
  "editorStyle": "file:./index.css",
  "style": "file:./style-index.css",
  "viewScript": "file:./view.js",
  "allowedBlocks": [
    "easy-smart-login/login-form-user-name"
  ]
}